src/__init__.py
src/common/__init__.py
src/common/action_status.py
src/common/constants.py
src/editor.py
src/main.py
src/retriever.py
src/test/__init__.py
src/test/test_editor.py
src/test/test_main.py
src/test/test_retriever.py
gha_pinner-1.0.2.dist-info/LICENSE
gha_pinner-1.0.2.dist-info/METADATA
gha_pinner-1.0.2.dist-info/WHEEL
gha_pinner-1.0.2.dist-info/entry_points.txt
gha_pinner-1.0.2.dist-info/RECORD
