Metadata-Version: 2.1
Name: gha-pinner
Version: 1.0.2
Summary: Pin GitHub Actions to specific commit SHAs for improved security
Home-page: https://github.com/sapasapasapa/gha-pinner
License: MIT
Keywords: github,actions,security,pin,sha
Author: Samuele Pasini
Author-email: sapa@bendingspoons.com
Requires-Python: >=3.8,<4.0
Classifier: Development Status :: 4 - Beta
Classifier: Intended Audience :: Developers
Classifier: License :: OSI Approved :: MIT License
Classifier: Programming Language :: Python :: 3
Classifier: Programming Language :: Python :: 3.8
Classifier: Programming Language :: Python :: 3.9
Classifier: Programming Language :: Python :: 3.10
Classifier: Programming Language :: Python :: 3.11
Classifier: Topic :: Security
Classifier: Topic :: Software Development :: Build Tools
Requires-Dist: requests (>=2.31.0,<3.0.0)
Requires-Dist: typer[all] (>=0.16.0,<0.17.0)
Project-URL: Repository, https://github.com/sapasapasapa/gha-pinner
